{
    "asset": {
        "id": "b657998c7917d17e633fedeb1881b9f9",
        "format": "jpg",
        "state": 2,
        "type": 1,
        "name": "tree27.jpg",
        "path": "https://ruststorage.blob.core.windows.net/rustpictures/tree27.jpg?sv=2019-02-02&ss=b&srt=sco&sp=rwdlac&se=2020-04-26T03:01:20Z&st=2020-04-09T19:01:20Z&spr=https&sig=pEV2Co%2FnWpUnCE6aCXvAPHb%2FeW82DV%2FYywL48bzmbVU%3D",
        "size": {
            "width": 3840,
            "height": 2160
        }
    },
    "regions": [
        {
            "id": "2RQP1e37L",
            "type": "POLYGON",
            "tags": [
                "treeforest"
            ],
            "boundingBox": {
                "height": 1847.776838546069,
                "width": 171.7221693625119,
                "left": 1880.4187232397717,
                "top": 5.819949281487742
            },
            "points": [
                {
                    "x": 1880.4187232397717,
                    "y": 1714.8309382924767
                },
                {
                    "x": 1902.3407023073264,
                    "y": 995.4395604395604
                },
                {
                    "x": 1916.9553550190296,
                    "y": 535.3212172442942
                },
                {
                    "x": 1895.033375951475,
                    "y": 5.819949281487742
                },
                {
                    "x": 2033.2635585156995,
                    "y": 12.781065088757396
                },
                {
                    "x": 2052.1408926022837,
                    "y": 1112.295012679628
                },
                {
                    "x": 2033.8725767126548,
                    "y": 1853.5967878275567
                },
                {
                    "x": 2033.8725767126548,
                    "y": 1849.9450549450546
                },
                {
                    "x": 1946.1846604424359,
                    "y": 1802.4725274725272
                },
                {
                    "x": 1946.1846604424359,
                    "y": 1798.8207945900253
                },
                {
                    "x": 1905.9943654852523,
                    "y": 1776.9103972950127
                }
            ]
        },
        {
            "id": "3DbEOWhcU",
            "type": "POLYGON",
            "tags": [
                "treeforest"
            ],
            "boundingBox": {
                "height": 569.6703296703297,
                "width": 65.76593720266413,
                "left": 912.1979810894387,
                "top": 1083.081149619611
            },
            "points": [
                {
                    "x": 945.0809496907707,
                    "y": 1652.7514792899408
                },
                {
                    "x": 930.4662969790676,
                    "y": 1199.9366018596788
                },
                {
                    "x": 912.1979810894387,
                    "y": 1101.3398140321217
                },
                {
                    "x": 930.4662969790676,
                    "y": 1083.081149619611
                },
                {
                    "x": 967.0029287583254,
                    "y": 1400.781910397295
                },
                {
                    "x": 977.9639182921028,
                    "y": 1649.0997464074387
                }
            ]
        },
        {
            "id": "GoveKNec2",
            "type": "POLYGON",
            "tags": [
                "treeforest"
            ],
            "boundingBox": {
                "height": 208.14877430262044,
                "width": 18.268315889628926,
                "left": 199.73360564343483,
                "top": 980.832628909552
            },
            "points": [
                {
                    "x": 203.3872688213606,
                    "y": 1181.6779374471682
                },
                {
                    "x": 199.73360564343483,
                    "y": 980.832628909552
                },
                {
                    "x": 218.00192153306375,
                    "y": 980.832628909552
                },
                {
                    "x": 218.00192153306375,
                    "y": 1188.9814032121724
                }
            ]
        }
    ],
    "version": "2.1.0"
}